.gitignore
Cargo.lock
Cargo.toml
LICENSE
MANIFEST.in
README.md
pyproject.toml
setup.py
.github/workflows/cargo-check.yml
.github/workflows/pypi-publish.yml
.github/workflows/rustfmt.yml
bagua-core-c/Cargo.toml
bagua-core-c/src/lib.rs
bagua-core-internal/Cargo.toml
bagua-core-internal/build.rs
bagua-core-internal/cpp/include/bagua_utils.h
bagua-core-internal/cpp/include/dbg.h
bagua-core-internal/kernels/bagua_kernels.cu
bagua-core-internal/src/cuda_utils.rs
bagua-core-internal/src/events.rs
bagua-core-internal/src/lib.rs
bagua-core-internal/src/comm_ops/centralized_full_precision_synchronous.rs
bagua-core-internal/src/comm_ops/centralized_low_precision_synchronous.rs
bagua-core-internal/src/comm_ops/decentralized_full_precision_synchronous.rs
bagua-core-internal/src/comm_ops/mod.rs
bagua-core-internal/src/comm_ops/python_ffi_op.rs
bagua-core-internal/src/communicators/mod.rs
bagua-core-internal/src/datatypes/mod.rs
bagua-core-internal/src/kernels/mod.rs
bagua-core-internal/src/resource_pool/mod.rs
bagua-core-internal/src/telemetry/mod.rs
bagua-core-internal/third_party/cub-1.8.0/.cproject
bagua-core-internal/third_party/cub-1.8.0/.project
bagua-core-internal/third_party/cub-1.8.0/CHANGE_LOG.TXT
bagua-core-internal/third_party/cub-1.8.0/LICENSE.TXT
bagua-core-internal/third_party/cub-1.8.0/README.md
bagua-core-internal/third_party/cub-1.8.0/common.mk
bagua-core-internal/third_party/cub-1.8.0/eclipse code style profile.xml
bagua-core-internal/third_party/cub-1.8.0/.settings/.gitignore
bagua-core-internal/third_party/cub-1.8.0/.settings/org.eclipse.cdt.codan.core.prefs
bagua-core-internal/third_party/cub-1.8.0/.settings/org.eclipse.cdt.core.prefs
bagua-core-internal/third_party/cub-1.8.0/.settings/org.eclipse.cdt.ui.prefs
bagua-core-internal/third_party/cub-1.8.0/.settings/org.eclipse.core.runtime.prefs
bagua-core-internal/third_party/cub-1.8.0/cub/cub.cuh
bagua-core-internal/third_party/cub-1.8.0/cub/util_allocator.cuh
python/bagua_core.egg-info/PKG-INFO
python/bagua_core.egg-info/SOURCES.txt
python/bagua_core.egg-info/dependency_links.txt
python/bagua_core.egg-info/not-zip-safe
python/bagua_core.egg-info/top_level.txt