Metadata-Version: 2.1
Name: bagua-core
Version: 0.2.0
Summary: Core communication lib for Bagua.
Home-page: https://github.com/BaguaSys/bagua-core
Author: Kuaishou AI Platform & DS3 Lab
Author-email: admin@mail.xrlian.com
License: UNKNOWN
Platform: UNKNOWN
Requires-Python: >=3.6
License-File: LICENSE
